alphalens/__init__.py
alphalens/performance.py
alphalens/plotting.py
alphalens/tears.py
alphalens/utils.py
alphalens/tests/__init__.py
alphalens/tests/test_performance.py
alphalens/tests/test_tears.py
alphalens/tests/test_utils.py
alphalens_qa-0.2.2.dist-info/LICENSE
alphalens_qa-0.2.2.dist-info/METADATA
alphalens_qa-0.2.2.dist-info/WHEEL
alphalens_qa-0.2.2.dist-info/top_level.txt
alphalens_qa-0.2.2.dist-info/RECORD
